[
  {
    "name": "Mt. Sabre West",
    "access_rules": [
      "$canMaybeReach|brynmaer, [$canReach|brynmaer]"
    ],
    "children": [
      {
        "name": "Mt. Sabre West: Tornado Bracelet",
        "access_rules": [
          "$negate|flag_wm, $canMaybeBreakSabreWestWalls, [$canBreakSabreWestWalls], $canClimbSlope",
          "flag_wm, $canClimbSlope, [$canBreakSabreWestWalls], $canOpenChest"
        ],
        "sections": [
          {
            "name": "Tornado Bracelet",
            "item_count": 1
          }
        ],
        "map_locations": [
          {
            "map": "map_sabre_west",
            "x": 520,
            "y": 165
          },
          {
            "map": "map_overworld",
            "x": 400,
            "y": 1400,
            "size": 45,
            "force_invisibility_rules": [
              "flag_eu"
            ]
          }
        ]
      },
      {
        "name": "Mt. Sabre West: Warp Boots",
        "access_rules": [
          "$negate|flag_wm, $canMaybeBreakSabreWestWalls, [$canBreakSabreWestWalls]",
          "flag_wm, d_sabrewest1, $canOpenChest",
          "flag_wm, $canBreakSabreWestWalls, $canOpenChest"
        ],
        "sections": [
          {
            "name": "Warp Boots",
            "item_count": 1
          }
        ],
        "map_locations": [
          {
            "map": "map_sabre_west",
            "x": 385,
            "y": 550,
            "force_invisibility_rules": [
              "flag_eu"
            ]
          },
          {
            "map": "map_overworld",
            "x": 400,
            "y": 1450,
            "size": 45,
            "force_invisibility_rules": [
              "flag_eu"
            ]
          }
        ]
      },
      {
        "name": "Mt. Sabre West: Medical Herb",
        "access_rules": [
          "$negate|flag_wm, $canMaybeBreakSabreWestWalls, [$canBreakSabreWestWalls]",
          "flag_wm, d_sabrewest2, [$canBreakSabreWestWalls], $canOpenChest",
          "flag_wm, flight, [$canBreakSabreWestWalls], $canOpenChest",
          "flag_wm, flag_gt, [$canBreakSabreWestWalls], $canOpenChest",
          "flag_wm, $canBreakSabreWestWalls"
        ],
        "sections": [
          {
            "name": "Medical Herb",
            "item_count": 1
          }
        ],
        "map_locations": [
          {
            "map": "map_sabre_west",
            "x": 860,
            "y": 130,
            "force_invisibility_rules": [
              "flag_eu"
            ]
          },
          {
            "map": "map_overworld",
            "x": 400,
            "y": 1500,
            "size": 45,
            "force_invisibility_rules": [
              "flag_eu"
            ]
          }
        ]
      },
      {
        "name": "Mt. Sabre West: Magic Ring",
        "access_rules": [
          "$negate|flag_wm, $canMaybeBreakSabreWestWalls, [$canBreakSabreWestWalls]",
          "flag_wm, d_sabrewest6, $canOpenChest",
          "flag_wm, $canBreakSabreWestWalls"
        ],
        "sections": [
          {
            "name": "Magic Ring",
            "item_count": 1
          }
        ],
        "map_locations": [
          {
            "map": "map_sabre_west",
            "x": 670,
            "y": 430,
            "force_invisibility_rules": [
              "flag_eu"
            ]
          },
          {
            "map": "map_overworld",
            "x": 450,
            "y": 1400,
            "size": 45,
            "force_invisibility_rules": [
              "flag_eu"
            ]
          }
        ]
      },
      {
        "name": "Mt. Sabre West: Tornel Reward",
        "access_rules": [
          "$negate|flag_wm, $canMaybeBreakSabreWestWalls, [$canBreakSabreWestWalls], $maybeHasTornelBracelet, [$hasTornelBracelet]",
          "flag_wm, d_sabrewest6, $maybeHasTornelBracelet, [$hasTornelBracelet]",
          "flag_wm, $canBreakSabreWestWalls, $maybeHasTornelBracelet, [$hasTornelBracelet]"
        ],
        "sections": [
          {
            "name": "Tornel - Show him Tornado Bracelet",
            "item_count": 1
          }
        ],
        "map_locations": [
          {
            "map": "map_sabre_west",
            "x": 630,
            "y": 430
          },
          {
            "map": "map_overworld",
            "x": 450,
            "y": 1450,
            "size": 45,
            "force_invisibility_rules": [
              "flag_eu"
            ]
          }
        ]
      },
      {
        "name": "Mt. Sabre West",
        "access_rules": [
          "$negate|d_sabrewest1_blocked"
        ],
        "sections": [
          {
            "name": "Exit to Warp Boots Ledge",
            "item_count": 0,
            "hosted_item": "d_sabrewest1"
          }
        ],
        "map_locations": [
          {
            "map": "map_sabre_west",
            "x": 77,
            "y": 530,
            "force_invisibility_rules": [
              "$negate|flag_wm",
              "$canBreakSabreWestWalls"
            ]
          }
        ]
      },
      {
        "name": "Mt. Sabre West",
        "access_rules": [
          "$negate|d_sabrewest2_blocked"
        ],
        "sections": [
          {
            "name": "Door to Room 2 (from Room 1)",
            "item_count": 0,
            "hosted_item": "d_sabrewest2"
          }
        ],
        "map_locations": [
          {
            "map": "map_sabre_west",
            "x": 335,
            "y": 460,
            "force_invisibility_rules": [
              "$negate|flag_wm",
              "$canBreakSabreWestWalls"
            ]
          }
        ]
      },
      {
        "name": "Mt. Sabre West",
        "access_rules": [
          "$negate|d_sabrewest3_blocked, d_sabrewest2",
          "$negate|d_sabrewest3_blocked, flight",
          "$negate|d_sabrewest3_blocked, flag_gt"
        ],
        "sections": [
          {
            "name": "Door to Room 3 (from Room 2)",
            "item_count": 0,
            "hosted_item": "d_sabrewest3"
          }
        ],
        "map_locations": [
          {
            "map": "map_sabre_west",
            "x": 1065,
            "y": 205,
            "force_invisibility_rules": [
              "$negate|flag_wm",
              "$canBreakSabreWestWalls"
            ]
          }
        ]
      },
      {
        "name": "Mt. Sabre West",
        "access_rules": [
          "$negate|d_sabrewest4_blocked, d_sabrewest2"
        ],
        "sections": [
          {
            "name": "Exit to Upper Mt. Sabre West",
            "item_count": 0,
            "hosted_item": "d_sabrewest4"
          }
        ],
        "map_locations": [
          {
            "map": "map_sabre_west",
            "x": 960,
            "y": 290,
            "force_invisibility_rules": [
              "$negate|flag_wm",
              "$canBreakSabreWestWalls",
              "flight",
              "flag_gt"
            ]
          }
        ]
      },
      {
        "name": "Mt. Sabre West",
        "access_rules": [
          "$negate|d_sabrewest5_blocked, d_sabrewest2, d_sabrewest4",
          "$negate|d_sabrewest5_blocked, d_sabrewest2, d_sabrewest3",
          "$negate|d_sabrewest5_blocked, flight",
          "$negate|d_sabrewest5_blocked, flag_gt"
        ],
        "sections": [
          {
            "name": "Door to Room 4 (from Room 3)",
            "item_count": 0,
            "hosted_item": "d_sabrewest5"
          }
        ],
        "map_locations": [
          {
            "map": "map_sabre_west",
            "x": 703,
            "y": 165,
            "force_invisibility_rules": [
              "$negate|flag_wm",
              "$canBreakSabreWestWalls"
            ]
          }
        ]
      },
      {
        "name": "Mt. Sabre West",
        "access_rules": [
          "$negate|d_sabrewest6_blocked, d_sabrewest5"
        ],
        "sections": [
          {
            "name": "Exit to Tornel's Ledge",
            "item_count": 0,
            "hosted_item": "d_sabrewest6"
          }
        ],
        "map_locations": [
          {
            "map": "map_sabre_west",
            "x": 660,
            "y": 320,
            "force_invisibility_rules": [
              "$negate|flag_wm",
              "$canBreakSabreWestWalls"
            ]
          }
        ]
      }
    ]
  }
]
